gcat_runner/__init__.py
gcat_runner/runner.py
gcat_runner-1.0.0.data/scripts/gcat_runner
gcat_runner-1.0.0.dist-info/LICENSE
gcat_runner-1.0.0.dist-info/METADATA
gcat_runner-1.0.0.dist-info/WHEEL
gcat_runner-1.0.0.dist-info/top_level.txt
gcat_runner-1.0.0.dist-info/RECORD
