Metadata-Version: 2.1
Name: gcat-runner
Version: 1.0.0
Summary: G-CAT Runner is a task runner for G-CAT Workflow and others.
Home-page: https://github.com/ncc-gap/GCATRunner.git
Author: Kenichi Chiba, Ai Okada and Yuichi Shiraishi
Author-email: genomon.devel@gmail.com
License: GPLv3
Keywords: cloud bioinformatics
Classifier: Development Status :: 3 - Alpha
Classifier: Intended Audience :: Science/Research
Classifier: Operating System :: Unix
Classifier: Programming Language :: Python :: 3.7
Classifier: Topic :: Scientific/Engineering :: Bio-Informatics
License-File: LICENSE
Requires-Dist: pyyaml
Requires-Dist: drmaa
